hdlcontroller/__init__.py
hdlcontroller/__main__.py
hdlcontroller/cli.py
hdlcontroller/hdlcontroller.py
hdlcontroller-0.5.2.dist-info/LICENSE
hdlcontroller-0.5.2.dist-info/METADATA
hdlcontroller-0.5.2.dist-info/WHEEL
hdlcontroller-0.5.2.dist-info/entry_points.txt
hdlcontroller-0.5.2.dist-info/top_level.txt
hdlcontroller-0.5.2.dist-info/RECORD
