Metadata-Version: 2.1
Name: hdlcontroller
Version: 0.5.2
Summary: HDLC controller
Author-email: Paul-Emmanuel Raoul <skyper@skyplabs.net>
License: The MIT License (MIT)
Project-URL: documentation, https://python-hdlc-controller.readthedocs.io/en/latest
Project-URL: repository, https://github.com/SkypLabs/python-hdlc-controller
Keywords: hdlc,controller
Classifier: Development Status :: 4 - Beta
Classifier: Intended Audience :: Developers
Classifier: Topic :: Software Development :: Libraries :: Python Modules
Classifier: Programming Language :: Python :: 3 :: Only
Classifier: Programming Language :: Python :: 3.7
Classifier: Programming Language :: Python :: 3.8
Classifier: Programming Language :: Python :: 3.9
Classifier: Programming Language :: Python :: 3.10
Classifier: Programming Language :: Python :: 3.11
Classifier: License :: OSI Approved :: MIT License
Requires-Python: <4,>=3.7
License-File: LICENSE
Requires-Dist: python4yahdlc >=1.3.5
Requires-Dist: pyserial >=3.0
Provides-Extra: dev
Requires-Dist: black ; extra == 'dev'
Requires-Dist: isort ; extra == 'dev'
Requires-Dist: ruff ; extra == 'dev'
Provides-Extra: docs
Requires-Dist: sphinx >=1.4.0 ; extra == 'docs'
Requires-Dist: sphinxcontrib-seqdiag >=0.8.5 ; extra == 'docs'
Requires-Dist: sphinx-argparse >=0.2.2 ; extra == 'docs'
Requires-Dist: sphinx-rtd-theme ; extra == 'docs'
Provides-Extra: tests
Requires-Dist: tox ; extra == 'tests'
